scrapy_metrics_exporter/__init__.py
scrapy_metrics_exporter/collectors.py
scrapy_metrics_exporter/extension.py
scrapy_metrics_exporter/metrics.py
scrapy_metrics_exporter/server.py
scrapy_metrics_exporter-0.1.0.dist-info/licenses/LICENSE
scrapy_metrics_exporter-0.1.0.dist-info/METADATA
scrapy_metrics_exporter-0.1.0.dist-info/WHEEL
scrapy_metrics_exporter-0.1.0.dist-info/top_level.txt
scrapy_metrics_exporter-0.1.0.dist-info/RECORD
