Metadata-Version: 2.4
Name: scrapy-metrics-exporter
Version: 0.1.0
Summary: Real-time metrics exporter for Scrapy with automatic collection of all stats
Author-email: Daniel Gines <dangines@gmail.com>
Maintainer-email: Daniel Gines <dangines@gmail.com>
License-Expression: MIT
Project-URL: Homepage, https://github.com/danielgines/scrapy-metrics-exporter
Project-URL: Repository, https://github.com/danielgines/scrapy-metrics-exporter
Keywords: scrapy,metrics,monitoring,observability,prometheus,exporter
Classifier: Development Status :: 3 - Alpha
Classifier: Framework :: Scrapy
Classifier: Intended Audience :: Developers
Classifier: Intended Audience :: System Administrators
Classifier: Operating System :: OS Independent
Classifier: Programming Language :: Python :: 3
Classifier: Programming Language :: Python :: 3.8
Classifier: Programming Language :: Python :: 3.9
Classifier: Programming Language :: Python :: 3.10
Classifier: Programming Language :: Python :: 3.11
Classifier: Programming Language :: Python :: 3.12
Classifier: Programming Language :: Python :: 3 :: Only
Classifier: Topic :: System :: Monitoring
Classifier: Topic :: Internet :: WWW/HTTP
Classifier: Topic :: Software Development :: Libraries :: Python Modules
Requires-Python: >=3.8
License-File: LICENSE
Requires-Dist: scrapy>=2.5.0
Requires-Dist: prometheus-client>=0.12.0
Requires-Dist: twisted>=21.0.0
Dynamic: license-file
